MANIFEST.in
license
readme.md
setup.py
alcss/__init__.py
alcss/run.py
alcss.egg-info/PKG-INFO
alcss.egg-info/SOURCES.txt
alcss.egg-info/dependency_links.txt
alcss.egg-info/entry_points.txt
alcss.egg-info/requires.txt
alcss.egg-info/top_level.txt