Metadata-Version: 2.1
Name: alcss
Version: 1.0.0
Summary: UNKNOWN
Home-page: https://github.com/clowzed/alcss.git
Author: Miasnenko Dmitry
Author-email: clowzed.work@gmail.com
License: UNKNOWN
Platform: UNKNOWN
License-File: license
